{
  "app": "GEO-SOP",
  "version": "0.3.36-dev",
  "channel": "desktop-dev",
  "released_at": "2026-07-16T05:08:48+08:00",
  "minimum_supported_version": "0.3.17-dev",
  "force": false,
  "notes": [
    "修复临时网络错误恢复后仍显示同步异常的问题。",
    "新增立即重连，可主动唤醒后台线程并马上重试云端心跳。",
    "心跳中断、登录失效与网络超时现在提供不同的操作提示。",
    "云端状态查询失败不再影响本地看板，后台同步仍会继续自动重试。",
    "Apple Silicon、Intel 与 Windows 安装包均通过原生启动验证，自动回归共 70 项。"
  ],
  "downloads": {
    "macos": {
      "name": "GEO-SOP-macOS-dev.dmg",
      "version": "0.3.36-dev",
      "url": "https://geo.allgood.cn/downloads/GEO-SOP-macOS-dev.dmg",
      "versioned_url": "https://geo.allgood.cn/downloads/GEO-SOP-v0.3.36-dev-macOS-Apple-Silicon.dmg",
      "size": "176 MB",
      "sha256": "f51f734ec6e637c8b1f982f6af475515d9c60eecfa4b52afa3f4d800cb79501d"
    },
    "macos_intel": {
      "name": "GEO-SOP-macOS-Intel-dev.dmg",
      "version": "0.3.36-dev",
      "url": "https://geo.allgood.cn/downloads/GEO-SOP-macOS-Intel-dev.dmg",
      "versioned_url": "https://geo.allgood.cn/downloads/GEO-SOP-v0.3.36-dev-macOS-Intel.dmg",
      "size": "182 MB",
      "sha256": "4075f18874886ba0c799a7a3b3d1b1ad111eb590f618c7f7e7234183f687cf98"
    },
    "windows": {
      "name": "GEO-SOP-Setup-dev.exe",
      "version": "0.3.36-dev",
      "url": "https://geo.allgood.cn/downloads/GEO-SOP-Setup-dev.exe",
      "versioned_url": "https://geo.allgood.cn/downloads/GEO-SOP-Setup-v0.3.36-dev.exe",
      "size": "146 MB",
      "sha256": "078dbf8782cf584fe1b4d4ed52497bcd5f9d06c6c6b0cc756fe597c747717134"
    }
  }
}
